lastpy/__init__.py
lastpy/extras.py
lastpy-1.0.8.dist-info/DESCRIPTION.rst
lastpy-1.0.8.dist-info/METADATA
lastpy-1.0.8.dist-info/RECORD
lastpy-1.0.8.dist-info/WHEEL
lastpy-1.0.8.dist-info/metadata.json
lastpy-1.0.8.dist-info/top_level.txt
