Metadata-Version: 2.0
Name: lastpy
Version: 1.0.8
Summary: A straightforward utility for scrobbling tracks to last.fm
Home-page: https://github.com/huberf/lastfm-scrobbler
Author: Noah Huber-Feely
Author-email: nhuberfeely@gmail.com
License: UNKNOWN
Download-URL: https://github.com/huberf/lastfm-scrobbler/archive/1.0.8.tar.gz
Keywords: lastfm
Platform: UNKNOWN
